{
  "subject": "EPH",
  "exam": "2020년도 2급 생활스포츠지도사 필기시험",
  "date": "2020-07-04",
  "questions": [
    {
      "id": "EPH-2020-1",
      "questionNumber": 1,
      "question": "유산소 시스템의 특징으로 적절하지 않은 것은?",
      "options": [
        {
          "id": 1,
          "content": "장시간의 저강도 운동 시 사용된다."
        },
        {
          "id": 2,
          "content": "무산소 시스템에 비해 ATP 합성률이 빠르다."
        },
        {
          "id": 3,
          "content": "산소를 이용하여 에너지 기질(substrate)을 분해한다."
        },
        {
          "id": 4,
          "content": "에너지 기질로 탄수화물과 지방을 모두 이용할 수 있다."
        }
      ],
      "answer": [
        2
      ],
      "explanation": {
        "correct": "유산소 시스템은 미토콘드리아 내의 복잡한 대사 경로를 거치므로, 세포질에서 즉각적으로 일어나는 **무산소 시스템(ATP-PC, 해당과정)에 비해 ATP 합성률(속도)이 현저히 느립니다.**",
        "distractors": [
          {
            "term": "저강도 장시간",
            "reason": "에너지 생산 효율이 높아 오랜 시간 지속하는 운동에 적합합니다."
          },
          {
            "term": "산소 이용",
            "reason": "산소를 최종 전자 수용체로 사용하여 다량의 ATP를 생성합니다."
          },
          {
            "term": "다양한 기질",
            "reason": "탄수화물, 지방, 단백질을 모두 연료로 사용할 수 있습니다."
          }
        ],
        "summary": "에너지 시스템 속도 - ATP-PC > 무산소 해당과정 > 유산소 시스템."
      },
      "category": "에너지 대사"
    },
    {
      "id": "EPH-2020-2",
      "questionNumber": 2,
      "question": "근육 내에서 산소를 운반하는 물질은?",
      "options": [
        {
          "id": 1,
          "content": "알부민(albumin)"
        },
        {
          "id": 2,
          "content": "신경전달물질(neurotransmitter)"
        },
        {
          "id": 3,
          "content": "마이오글로빈(myoglobin)"
        },
        {
          "id": 4,
          "content": "아세틸콜린(acetylcholine)"
        }
      ],
      "answer": [
        3
      ],
      "explanation": {
        "correct": "**마이오글로빈(Myoglobin)**은 근세포 내에 존재하며, 헤모글로빈으로부터 산소를 받아 근육 내 미토콘드리아로 전달하는 역할을 합니다.",
        "distractors": [
          {
            "term": "알부민",
            "reason": "혈장 단백질로 삼투압 유지 및 물질 운반을 담당합니다."
          },
          {
            "term": "아세틸콜린",
            "reason": "신경근 접합부에서 근수축 신호를 전달하는 신경전달물질입니다."
          }
        ],
        "summary": "산소 운반 - 혈액 중(헤모글로빈), 근육 중(마이오글로빈)."
      },
      "category": "혈액과 순환"
    },
    {
      "id": "EPH-2020-3",
      "questionNumber": 3,
      "question": "고강도 운동 시 ATP 합성에 사용되는 주요 기질(substrate)로 적절한 것은?",
      "options": [
        {
          "id": 1,
          "content": "젖산"
        },
        {
          "id": 2,
          "content": "지방"
        },
        {
          "id": 3,
          "content": "근육 단백질"
        },
        {
          "id": 4,
          "content": "근육 글리코겐"
        }
      ],
      "answer": [
        4
      ],
      "explanation": {
        "correct": "운동 강도가 높아질수록 산소 공급이 부족해져 빠르게 분해될 수 있는 탄수화물 의존도가 높아집니다. 특히 근육 내에 저장된 **글리코겐**이 고강도 운동의 핵심 연료입니다.",
        "distractors": [
          {
            "term": "지방",
            "reason": "저강도 운동에서 주로 사용되며, 분해 속도가 느려 고강도 운동에는 부적합합니다."
          },
          {
            "term": "단백질",
            "reason": "기아 상태나 극도의 장시간 운동 외에는 주료 연료로 쓰이지 않습니다."
          }
        ],
        "summary": "강도와 기질 - 저강도(지방 위주), 고강도(탄수화물 위주)."
      },
      "category": "에너지 대사"
    },
    {
      "id": "EPH-2020-4",
      "questionNumber": 4,
      "question": "<보기>가 설명하는 호르몬은?",
      "view": {
        "text": [
          "부신수질로부터 분비된다.",
          "운동의 강도와 시간이 증가함에 따라 분비가 증가하며, 지방조직과 근육 내 지방의 분해를 촉진하는 역할을 한다."
        ]
      },
      "options": [
        {
          "id": 1,
          "content": "인슐린(insulin)"
        },
        {
          "id": 2,
          "content": "글루카곤(glucagon)"
        },
        {
          "id": 3,
          "content": "에피네프린(epinephrine)"
        },
        {
          "id": 4,
          "content": "알도스테론(aldosterone)"
        }
      ],
      "answer": [
        3
      ],
      "explanation": {
        "correct": "부신수질에서 분비되는 **에피네프린**은 운동 중 에너지(지방, 당) 동원을 강력하게 촉진하는 대표적인 호르몬입니다.",
        "summary": "부신 호르몬 - 수질(에피네프린, 노르에피네프린), 피질(코티졸, 알도스테론)."
      },
      "category": "내분비계"
    },
    {
      "id": "EPH-2020-5",
      "questionNumber": 5,
      "question": "장기간의 저항성 트레이닝에 따른 골격근의 적응으로 적절하지 않은 것은?",
      "options": [
        {
          "id": 1,
          "content": "근형질(sarcoplasm)의 양이 증가한다."
        },
        {
          "id": 2,
          "content": "근원섬유(myofibril)의 수가 증가한다."
        },
        {
          "id": 3,
          "content": "속근섬유(type II fiber)의 단면적이 증가한다."
        },
        {
          "id": 4,
          "content": "미토콘드리아(mitochondria)의 밀도가 증가한다."
        }
      ],
      "answer": [
        4
      ],
      "explanation": {
        "correct": "저항성 트레이닝(근력 운동)은 근육의 크기를 키우는 데 집중하므로, 수축 단백질 증가에 비해 **미토콘드리아 밀도는 상대적으로 감소**하거나 유지되는 경향을 보입니다. (미토콘드리아 증가는 유산소 훈련의 특징입니다.)",
        "distractors": [
          {
            "term": "근비대",
            "reason": "근원섬유 수와 근형질 양이 늘어나 근육 단면적이 커집니다."
          },
          {
            "term": "속근 발달",
            "reason": "특히 힘을 담당하는 속근 섬유의 성장이 두드러집니다."
          }
        ],
        "summary": "트레이닝 적응 - 저항 훈련(근비대, 수축 단백질↑), 유산소 훈련(미토콘드리아, 모세혈관↑)."
      },
      "category": "트레이닝 적응"
    },
    {
      "id": "EPH-2020-6",
      "questionNumber": 6,
      "question": "<보기>의 ㉠과 ㉡에 들어갈 용어를 바르게 나열한 것은?",
      "view": {
        "blanks": [
          "지구성 트레이닝에 대한 적응으로 최대 동-정맥산소차는 ( ㉠ )하고, 최대 1회박출량(stroke volume)은 ( ㉡ )한다."
        ]
      },
      "options": [
        {
          "id": 1,
          "content": "㉠-증가 / ㉡-증가"
        },
        {
          "id": 2,
          "content": "㉠-증가 / ㉡-감소"
        },
        {
          "id": 3,
          "content": "㉠-감소 / ㉡-감소"
        },
        {
          "id": 4,
          "content": "㉠-감소 / ㉡-증가"
        }
      ],
      "answer": [
        1
      ],
      "explanation": {
        "correct": "유산소 훈련 적응으로 심장이 튼튼해져 **1회 박출량이 증가(㉡)**하며, 근육의 산소 추출 능력이 좋아져 **동-정맥산소차가 증가(㉠)**합니다.",
        "summary": "VO2max 결정 요인(Fick 공식) - VO2 = SV × HR × (a-v)O2 diff. 훈련 시 SV와 동정맥산소차가 모두 증가하여 최대산소섭취량이 향상됩니다."
      },
      "category": "트레이닝 적응"
    },
    {
      "id": "EPH-2020-7",
      "questionNumber": 7,
      "question": "<보기>의 신경세포 구조 및 전기적 활동에 관한 적절한 설명을 고른 것은?",
      "view": {
        "list": [
          {
            "label": "㉠",
            "content": [
              "안정 시 신경세포 막의 안쪽은 Na+의 농도가 높고, 바깥쪽은 K+의 농도가 높다."
            ]
          },
          {
            "label": "㉡",
            "content": [
              "역치(threshold)는 신경세포 막의 차등성전위(graded potential)가 안정막전위(resting membrane potential)로 바뀌는 시점을 말한다."
            ]
          },
          {
            "label": "㉢",
            "content": [
              "활동전위(action potential)는 신경세포 막의 탈분극(depolarization)을 유도한다."
            ]
          },
          {
            "label": "㉣",
            "content": [
              "신경세포는 신경-근접합부(neuromuscular junction)를 통해 근섬유와 상호신호전달을 한다."
            ]
          }
        ]
      },
      "options": [
        {
          "id": 1,
          "content": "㉠, ㉡"
        },
        {
          "id": 2,
          "content": "㉠, ㉣"
        },
        {
          "id": 3,
          "content": "㉡, ㉢"
        },
        {
          "id": 4,
          "content": "㉢, ㉣"
        }
      ],
      "answer": [
        4
      ],
      "explanation": {
        "correct": "자극이 역치를 넘으면 **탈분극(㉢)**이 일어나 활동전위가 발생하며, 운동신경과 근육이 만나는 **신경-근접합부(㉣)**를 통해 신호가 전달됩니다.",
        "distractors": [
          {
            "term": "㉠",
            "reason": "안정 시 안쪽은 **K+**가 높고, 바깥쪽은 **Na+**가 높습니다."
          },
          {
            "term": "㉡",
            "reason": "역치는 차등성전위가 **활동전위**로 전환되는 문턱값을 의미합니다."
          }
        ],
        "summary": "막전위 유지 - Na-K 펌프에 의해 농도 구배 유지 (안쪽 K+, 바깥쪽 Na+)."
      },
      "category": "신경계"
    },
    {
      "id": "EPH-2020-8",
      "questionNumber": 8,
      "question": "적혈구용적률(hematocrit)에 관한 설명으로 적절한 것은?",
      "options": [
        {
          "id": 1,
          "content": "높은 적혈구용적률(60% 이상)은 혈액의 흐름을 수월하게 한다."
        },
        {
          "id": 2,
          "content": "일반적으로 성인 여성이 성인 남성보다 높은 적혈구용적률을 보인다."
        },
        {
          "id": 3,
          "content": "전체 혈액량 대비 혈장(plasma)량의 비율이 높을수록 적혈구용적률은 낮다."
        },
        {
          "id": 4,
          "content": "지구성 트레이닝에 대한 적응으로 혈장량이 감소하여 적혈구용적률은 증가한다."
        }
      ],
      "answer": [
        3
      ],
      "explanation": {
        "correct": "적혈구용적률은 전체 혈액 중 적혈구가 차지하는 비율입니다. 따라서 수분 성분인 **혈장량이 많아질수록 비율은 상대적으로 낮아집니다.**",
        "distractors": [
          {
            "term": "점성",
            "reason": "적혈구가 너무 많으면(60%↑) 혈액이 끈적해져 흐름이 방해됩니다."
          },
          {
            "term": "성별 차이",
            "reason": "일반적으로 남성이 여성보다 높습니다."
          },
          {
            "term": "훈련 적응",
            "reason": "유산소 훈련 시 혈장량이 크게 늘어나 적혈구용적률은 소폭 **감소(희석)**하는 경향이 있습니다."
          }
        ],
        "summary": "적혈구용적률(Hct) - 정상 범위 약 40~45%."
      },
      "category": "혈액과 순환"
    },
    {
      "id": "EPH-2020-9",
      "questionNumber": 9,
      "question": "근세사 활주설(sliding filament theory)에 관한 설명으로 적절하지 않은 것은?",
      "options": [
        {
          "id": 1,
          "content": "액틴(actin)은 근절(sarcomere)의 중앙부위로 마이오신(myosin)을 잡아당긴다."
        },
        {
          "id": 2,
          "content": "마이오신 머리(myosin head)에 있는 인산기(Pi)가 방출되면서 파워 스트로크(power stroke)가 일어난다."
        },
        {
          "id": 3,
          "content": "활동전위는 근형질세망(sarcoplasmic reticulum)으로부터 나온 Ca2+을 근형질(sarcoplasm) 내로 유입하게 한다."
        },
        {
          "id": 4,
          "content": "Ca2+은 액틴 세사의 트로포닌(troponin)과 결합하고 트로포닌은 트로포마이오신(tropomyosin)을 이동시켜 마이오신 머리가 액틴과 결합할 수 있도록 한다."
        }
      ],
      "answer": [
        1
      ],
      "explanation": {
        "correct": "수축 시 **마이오신 머리가 액틴을 근절 중앙(H-zone) 방향으로 잡아당기는 것**이지, 액틴이 마이오신을 당기는 것이 아닙니다.",
        "distractors": [
          {
            "term": "에너지 사용",
            "reason": "ATP가 분해된 후 인산기가 방출되는 시점에 강력한 힘(파워 스트로크)이 발생합니다."
          },
          {
            "term": "칼슘의 역할",
            "reason": "SR에서 나온 칼슘이 트로포닌과 결합하여 액틴의 결합 부위를 노출시킵니다."
          }
        ],
        "summary": "활주설 - 필라멘트 자체의 길이는 변하지 않고, 서로 겹쳐지는 정도가 변하며 수축함."
      },
      "category": "골격근"
    },
    {
      "id": "EPH-2020-10",
      "questionNumber": 10,
      "question": "<보기>는 산소-헤모글로빈 해리 곡선의 운동 시 변화에 관한 설명이다. ㉠, ㉡, ㉢, ㉣에 들어갈 용어를 바르게 나열한 것은?",
      "view": {
        "media": {
          "type": "IMAGE",
          "url": "/exam/EPH-2020-10.webp",
          "alt": "산소-헤모글로빈 해리 곡선의 운동 시 변화"
        },
        "blanks": [
          "심부체온이 증가하여 산소-헤모글로빈 해리 곡선은 ( ㉠ )으로 이동하며, 헤모글로빈의 산소 친화력을 ( ㉡ )시킨다.",
          "신체의 pH가 감소하여 산소-헤모글로빈 해리 곡선은 ( ㉢ )으로 이동하며, 헤모글로빈의 산소 친화력을 ( ㉣ )시킨다."
        ]
      },
      "options": [
        {
          "id": 1,
          "content": "㉠-오른쪽 / ㉡-감소 / ㉢-오른쪽 / ㉣-감소"
        },
        {
          "id": 2,
          "content": "㉠-오른쪽 / ㉡-증가 / ㉢-왼쪽 / ㉣-감소"
        },
        {
          "id": 3,
          "content": "㉠-왼쪽 / ㉡-증가 / ㉢-왼쪽 / ㉣-증가"
        },
        {
          "id": 4,
          "content": "㉠-왼쪽 / ㉡-감소 / ㉢-오른쪽 / ㉣-증가"
        }
      ],
      "answer": [
        1
      ],
      "explanation": {
        "correct": "체온 상승과 pH 감소(산성)는 모두 곡선을 **오른쪽**으로 이동시킵니다. 이는 산소 친화력을 **감소**시켜 산소가 헤모글로빈으로부터 잘 떨어져 나오게 함으로써 근육에 산소 공급을 돕는 '보어 효과'입니다.",
        "summary": "우측 이동 요인(산소 해리 촉진) - 온도↑, pH↓, PCO2↑, 2,3-DPG↑."
      },
      "category": "혈액과 순환"
    },
    {
      "id": "EPH-2020-11",
      "questionNumber": 11,
      "question": "<보기>의 근수축 유형에 따른 힘-속도-파워 간의 관계에 관한 설명으로 적절한 것만 고른 것은?",
      "view": {
        "list": [
          {
            "label": "㉠",
            "content": [
              "신장성 수축은 수축 속도가 빠를수록 힘이 더 증가한다."
            ]
          },
          {
            "label": "㉡",
            "content": [
              "단축성 수축은 수축 속도가 빠를수록 최대파워가 더 증가한다."
            ]
          },
          {
            "label": "㉢",
            "content": [
              "동일 근육에서의 느린 단축성 수축은 빠른 신장성 수축에 비해 더 큰 힘이 생성된다."
            ]
          },
          {
            "label": "㉣",
            "content": [
              "동일 근육에서의 신장성 수축은 단축성 수축에 비해 같은 속도에서 더 큰 힘이 생성된다."
            ]
          }
        ]
      },
      "options": [
        {
          "id": 1,
          "content": "㉠, ㉢"
        },
        {
          "id": 2,
          "content": "㉠, ㉢, ㉣"
        },
        {
          "id": 3,
          "content": "㉠, ㉣"
        },
        {
          "id": 4,
          "content": "㉡, ㉢"
        }
      ],
      "answer": [
        3
      ],
      "explanation": {
        "correct": "신장성 수축은 속도가 빠를수록 힘이 증가(㉠)하며, 모든 속도 영역에서 단축성 수축보다 더 큰 힘을 발휘(㉣)합니다.",
        "distractors": [
          {
            "term": "㉡",
            "reason": "단축성 수축에서 파워는 일정 속도까지는 증가하지만, 속도가 너무 빠르면 힘이 급격히 줄어들어 파워가 다시 감소합니다."
          },
          {
            "term": "㉢",
            "reason": "신장성 수축이 단축성 수축보다 항상 더 큰 힘을 생성합니다."
          }
        ],
        "summary": "힘-속도 관계 - 단축성(반비례), 신장성(비례)."
      },
      "category": "골격근"
    },
    {
      "id": "EPH-2020-12",
      "questionNumber": 12,
      "question": "장시간의 운동 시 발생하는 탈수현상이 심혈관계에 미치는 영향으로 적절한 것은?",
      "options": [
        {
          "id": 1,
          "content": "혈액량이 점차 증가한다."
        },
        {
          "id": 2,
          "content": "심박수가 점차 증가한다."
        },
        {
          "id": 3,
          "content": "심실의 확장기말 용량(end-diastolic volume)이 점차 증가한다."
        },
        {
          "id": 4,
          "content": "우심방으로 돌아오는 정맥환류(venous return)의 양이 점차 증가한다."
        }
      ],
      "answer": [
        2
      ],
      "explanation": {
        "correct": "탈수로 혈장량이 줄어들면 1회 박출량이 감소합니다. 이를 보상하여 심박출량을 유지하기 위해 **심박수가 점진적으로 증가**하는데, 이를 '심혈관 표류(Cardiovascular drift)'라고 합니다.",
        "summary": "탈수 영향 - 혈액량↓ -> 정맥환류↓ -> 1회박출량↓ -> 보상적 심박수↑."
      },
      "category": "심폐계"
    },
    {
      "id": "EPH-2020-13",
      "questionNumber": 13,
      "question": "운동단위(motor unit)에 관한 설명으로 적절한 것은?",
      "options": [
        {
          "id": 1,
          "content": "하나의 근섬유와 연결되는 여러 개의 알파운동뉴런을 말한다."
        },
        {
          "id": 2,
          "content": "Type I 운동단위는 Type II 운동단위 보다 단위 당 근섬유 수가 많다."
        },
        {
          "id": 3,
          "content": "Type I 운동단위는 Type II 운동단위 보다 일반적으로 먼저 동원된다."
        },
        {
          "id": 4,
          "content": "Type I 운동단위는 Type II 운동단위 보다 알파운동뉴런의 크기가 크다."
        }
      ],
      "answer": [
        3
      ],
      "explanation": {
        "correct": "'크기의 원리'에 따라 자극 역치가 낮고 크기가 작은 **지근(Type I) 운동단위가 고강도 속근보다 항상 먼저 동원**됩니다.",
        "distractors": [
          {
            "term": "정의",
            "reason": "'하나의' 운동뉴런과 그에 지배받는 '여러 개'의 근섬유 묶음입니다."
          },
          {
            "term": "특성",
            "reason": "속근(Type II)이 뉴런의 크기도 더 크고, 지배하는 섬유 수도 더 많습니다."
          }
        ],
        "summary": "동원 순서 - Type I -> Type IIa -> Type IIx."
      },
      "category": "신경계"
    },
    {
      "id": "EPH-2020-14",
      "questionNumber": 14,
      "question": "<보기>가 설명하는 호르몬은?",
      "view": {
        "text": [
          "운동 시 뇌하수체 전엽에서 분비된다.",
          "트라이아이오드타이로닌(T3)과 티록신(T4) 호르몬의 분비를 조절한다."
        ]
      },
      "options": [
        {
          "id": 1,
          "content": "갑상선자극호르몬(thyroid-stimulating hormone)"
        },
        {
          "id": 2,
          "content": "노르에피네프린(norepinephrine)"
        },
        {
          "id": 3,
          "content": "성장호르몬(growth hormone)"
        },
        {
          "id": 4,
          "content": "인슐린(insulin)"
        }
      ],
      "answer": [
        1
      ],
      "explanation": {
        "correct": "명칭 그대로 **갑상선자극호르몬(TSH)**은 갑상선을 자극하여 대사 조절 호르몬인 T3, T4 분비를 유도합니다.",
        "summary": "뇌하수체 전엽 호르몬 - 성장호르몬, TSH, ACTH, FSH, LH, 프로락틴."
      },
      "category": "내분비계"
    },
    {
      "id": "EPH-2020-15",
      "questionNumber": 15,
      "question": "<보기>에서 ㉠과 ㉡의 근섬유 유형별 특성으로 적절한 것은?",
      "view": {
        "blanks": [
          "훈련되지 않은 사람과 비교하여 단거리 선수의 장딴지 근육은 주로 ( ㉠ )의 비율이 높고, 장거리 수영선수의 팔 근육은 ( ㉡ )의 비율이 높은 경향이 있다."
        ]
      },
      "options": [
        {
          "id": 1,
          "content": "㉠은 ㉡에 비하여 수축 속도가 느리다."
        },
        {
          "id": 2,
          "content": "㉠은 ㉡에 비하여 피로에 대한 저항성이 낮다."
        },
        {
          "id": 3,
          "content": "㉡은 ㉠에 비하여 미토콘드리아 밀도가 낮다."
        },
        {
          "id": 4,
          "content": "㉡은 ㉠에 비하여 해당 능력(glycolytic capacity)이 높다."
        }
      ],
      "answer": [
        2
      ],
      "explanation": {
        "correct": "단거리 선수는 속근(㉠, Type II) 비율이 높고, 장거리 선수는 지근(㉡, Type I) 비율이 높습니다. **속근(㉠)은 지근(㉡)에 비해 피로 저항성이 매우 낮습니다.**",
        "summary": "- **속근(Type II)**: 수축 빠름, 힘 셈, 미토콘드리아 적음, 피로에 약함.\n- **지근(Type I)**: 수축 느림, 힘 약함, 미토콘드리아 많음, 피로에 강함."
      },
      "category": "골격근"
    },
    {
      "id": "EPH-2020-16",
      "questionNumber": 16,
      "question": "<보기>가 설명하는 것은?",
      "view": {
        "text": [
          "우심방 벽에 위치한다.",
          "심장수축을 위한 전기적 자극이 시작되므로 페이스메이커(pacemaker)라고 한다."
        ]
      },
      "options": [
        {
          "id": 1,
          "content": "동방결절(SA node)"
        },
        {
          "id": 2,
          "content": "퍼킨제섬유(purkinje fibers)"
        },
        {
          "id": 3,
          "content": "방실다발(AV bundle)"
        },
        {
          "id": 4,
          "content": "삼첨판막(tricuspid valve)"
        }
      ],
      "answer": [
        1
      ],
      "explanation": {
        "correct": "심장의 전기적 신호를 스스로 만들어내는 심장 전도계의 시작점은 **동방결절(SA node)**입니다.",
        "summary": "심장 전도 순서 - 동방결절(SA) -> 방실결절(AV) -> 방실다발(His bundle) -> 퍼킨제 섬유."
      },
      "category": "심폐계"
    },
    {
      "id": "EPH-2020-17",
      "questionNumber": 17,
      "question": "저강도(1RM의 30~40%)의 고반복(세트당 20~25회) 저항성 트레이닝에 따른 골격근의 주요 변화로 적절한 것은?",
      "options": [
        {
          "id": 1,
          "content": "근비대(muscle hypertrophy)"
        },
        {
          "id": 2,
          "content": "근력(muscle strength) 향상"
        },
        {
          "id": 3,
          "content": "근파워(muscle power) 향상"
        },
        {
          "id": 4,
          "content": "근지구력(muscle endurance) 향상"
        }
      ],
      "answer": [
        4
      ],
      "explanation": {
        "correct": "낮은 강도로 많은 횟수를 반복하는 훈련은 근육이 피로에 견디는 능력인 **근지구력**을 발달시키는 전형적인 방법입니다.",
        "summary": "저항 훈련 목표 - 고강도/저반복(근력, 파워), 저강도/고반복(근지구력), 중강도/중반복(근비대)."
      },
      "category": "트레이닝 적응"
    },
    {
      "id": "EPH-2020-18",
      "questionNumber": 18,
      "question": "<보기>에서 인체 내 가스교환에 관한 설명 중 ㉠과 ㉡에 들어갈 용어를 바르게 나열한 것은?",
      "view": {
        "blanks": [
          "운동 시 폐포로 유입된 ( ㉠ )는 폐 모세혈관으로 확산된다.",
          "운동 시 근육에서 생성된 ( ㉡ )는 모세혈관으로 확산된다."
        ]
      },
      "options": [
        {
          "id": 1,
          "content": "㉠-산소 / ㉡-산소"
        },
        {
          "id": 2,
          "content": "㉠-산소 / ㉡-이산화탄소"
        },
        {
          "id": 3,
          "content": "㉠-이산화탄소 / ㉡-이산화탄소"
        },
        {
          "id": 4,
          "content": "㉠-이산화탄소 / ㉡-산소"
        }
      ],
      "answer": [
        2
      ],
      "explanation": {
        "correct": "폐에서는 외부에서 들어온 **산소(㉠)**가 혈액으로 이동하고, 조직(근육)에서는 대사 결과 발생한 **이산화탄소(㉡)**가 혈액으로 배출됩니다.",
        "summary": "가스 교환 방향 - 폐(O2 흡수, CO2 배출) vs 조직(O2 공급, CO2 회수)."
      },
      "category": "심폐계"
    },
    {
      "id": "EPH-2020-19",
      "questionNumber": 19,
      "question": "운동 시 교감신경계의 활성화에 따른 반응으로 적절하지 않은 것은?",
      "options": [
        {
          "id": 1,
          "content": "심박수가 증가한다."
        },
        {
          "id": 2,
          "content": "소화기계 활동이 증가한다."
        },
        {
          "id": 3,
          "content": "골격근의 혈류량이 증가한다."
        },
        {
          "id": 4,
          "content": "호흡수 및 가스교환율이 증가한다."
        }
      ],
      "answer": [
        2
      ],
      "explanation": {
        "correct": "운동 중 활성화되는 교감신경은 활동 근육으로 에너지를 집중하기 위해 **소화기계의 혈류를 줄이고 활동(소화, 흡수)을 억제**합니다.",
        "summary": "교감신경 효과 - HR↑, 호흡↑, 활동 근육 혈관 확장, 비활동 조직(소화기, 신장) 혈관 수축."
      },
      "category": "신경계"
    },
    {
      "id": "EPH-2020-20",
      "questionNumber": 20,
      "question": "장기간의 유산소 트레이닝에 따른 심혈관계의 적응으로 적절하지 않은 것은?",
      "options": [
        {
          "id": 1,
          "content": "안정시 심박수 감소"
        },
        {
          "id": 2,
          "content": "최대산소섭취량(V̇O2max) 증가"
        },
        {
          "id": 3,
          "content": "최대 심박출량(cardiac output) 증가"
        },
        {
          "id": 4,
          "content": "안정시 1회박출량(stroke volume) 감소"
        }
      ],
      "answer": [
        4
      ],
      "explanation": {
        "correct": "유산소 훈련을 하면 심장이 커지고 수축력이 좋아져 **안정 시 1회 박출량은 현저히 증가**합니다. 이 덕분에 심장이 적게 뛰어도 필요한 혈액량을 보낼 수 있어 안정 시 심박수는 감소(서맥)하게 됩니다.",
        "summary": "스포츠 심장 - SV↑, HR↓ (경제적인 심장 활동)."
      },
      "category": "트레이닝 적응"
    }
  ]
}