{
  "subject": "SSO",
  "exam": "2022년도 2급류 체육지도자 필기시험",
  "date": "2022-05-07",
  "questions": [
    {
      "id": "SSO-2022-1",
      "questionNumber": 1,
      "question": "<보기>에서 스포츠의 사회적 기능을 설명한 파슨즈(T. Parsons) AGIL 모형의 구성요소는?",
      "view": {
        "text": [
          "스포츠는 사회구성원에게 현실에 적합한 사고, 감정, 행동양식 등을 학습할 수 있는 장을 마련해준다.",
          "스포츠는 개인의 체력 및 건강증진을 도모하여 효율적으로 사회활동에 참여할 수 있게 한다."
        ]
      },
      "options": [
        {
          "id": 1,
          "content": "적응"
        },
        {
          "id": 2,
          "content": "목표성취"
        },
        {
          "id": 3,
          "content": "사회통합"
        },
        {
          "id": 4,
          "content": "체제유지 및 관리"
        }
      ],
      "answer": [
        1
      ],
      "explanation": {
        "correct": "파슨즈의 AGIL 모형 중 **적응(Adaptation)**은 체계가 외부 환경으로부터 자원을 확보하고 분배하여 체계를 유지하는 기능입니다. 스포츠를 통해 건강을 증진하고 사회에 필요한 소양을 배우는 과정은 환경에 대한 개인의 적응력을 높이는 활동입니다.",
        "distractors": [
          {
            "term": "목표성취",
            "reason": "사회의 공동 목표를 달성하기 위해 자원을 동원하는 기능입니다."
          },
          {
            "term": "사회통합",
            "reason": "구성원 간의 결속을 다지고 갈등을 조정하는 기능입니다."
          },
          {
            "term": "체제유지 및 관리",
            "reason": "사회의 핵심 가치와 규범을 보존하고 전수하는 기능입니다."
          }
        ],
        "summary": "파슨즈의 AGIL 기능 - 적응(A), 목표성취(G), 통합(I), 잠재적 체제유지(L)."
      }
    },
    {
      "id": "SSO-2022-2",
      "questionNumber": 2,
      "question": "에티즌(D. Eitzen)과 세이지(G. Sage)가 제시한 스포츠의 정치적 속성이 아닌 것은?",
      "options": [
        {
          "id": 1,
          "content": "보수성"
        },
        {
          "id": 2,
          "content": "대표성"
        },
        {
          "id": 3,
          "content": "권력투쟁"
        },
        {
          "id": 4,
          "content": "상호배타성"
        }
      ],
      "answer": [
        4
      ],
      "explanation": {
        "correct": "**상호배타성**은 정치와 스포츠가 서로 독립적임을 의미하지만, 실제로는 양자가 서로의 목적을 위해 긴밀히 결합하는 **상호의존성**이 더 본질적인 정치적 속성입니다.",
        "distractors": [
          {
            "term": "보수성",
            "reason": "기존 사회 질서를 유지하려는 성질입니다."
          },
          {
            "term": "대표성",
            "reason": "특정 집단이나 국가를 상징하고 대표하는 성질입니다."
          },
          {
            "term": "권력투쟁",
            "reason": "영향력을 확보하기 위해 이해관계자들이 대립하는 속성입니다."
          }
        ],
        "summary": "스포츠의 정치적 속성 - 보수성, 대표성, 권력투쟁, 상호의존성, 긴장 관계."
      }
    },
    {
      "id": "SSO-2022-3",
      "questionNumber": 3,
      "question": "<보기>에서 설명하는 사회학습이론의 구성요소는?",
      "view": {
        "text": [
          {
            "text": "상과 벌은 행동의 학습과 수행에 긍정적·부정적 영향을 미친다."
          },
          {
            "text": "스포츠 현장에서 스포츠에 내재된 가치, 태도, 규범에 그릇된 행위는 벌을 통해 중단되거나 회피된다."
          }
        ]
      },
      "options": [
        {
          "id": 1,
          "content": "강화"
        },
        {
          "id": 2,
          "content": "코칭"
        },
        {
          "id": 3,
          "content": "관찰학습"
        },
        {
          "id": 4,
          "content": "역할학습"
        }
      ],
      "answer": [
        1
      ],
      "explanation": {
        "correct": "**강화(Reinforcement)**는 특정 행동 이후에 주어지는 반응(보상이나 처벌)을 통해 그 행동의 빈도를 조절하는 기전입니다. 지문의 '상과 벌을 통한 영향'은 강화의 원리를 설명합니다.",
        "distractors": [
          {
            "term": "코칭",
            "reason": "직접적인 가르침을 통한 학습."
          },
          {
            "term": "관찰학습",
            "reason": "타인의 행동 모방."
          },
          {
            "term": "역할학습",
            "reason": "부여된 지위에 따른 기대 내면화입니다."
          }
        ],
        "summary": "사회학습이론의 3대 요소 - 강화, 코칭, 모방."
      }
    },
    {
      "id": "SSO-2022-4",
      "questionNumber": 4,
      "question": "<보기>에 해당하는 스포츠사회화 과정이 바르게 연결된 것은?",
      "view": {
        "list": [
          {
            "label": "㉠",
            "content": [
              "손목수술 후유증으로 인해 골프선수를 그만두게 되었다."
            ]
          },
          {
            "label": "㉡",
            "content": [
              "골프의 매력에 빠져 골프선수가 되어 사회성, 체력, 준법정신이 함양되었다."
            ]
          },
          {
            "label": "㉢",
            "content": [
              "아빠와 함께 골프연습장에 자주 가면서 골프를 배우게 되었다."
            ]
          },
          {
            "label": "㉣",
            "content": [
              "골프선수 은퇴 후 골프아카데미 원장으로 부임하면서 골프꿈나무를 양성하게 되었다."
            ]
          }
        ]
      },
      "options": [
        {
          "id": 1,
          "content": "㉠-스포츠로의 재사회화 / ㉡-스포츠를 통한 사회화 / ㉢-스포츠로의 사회화 / ㉣-스포츠 탈사회화"
        },
        {
          "id": 2,
          "content": "㉠-스포츠로의 재사회화 / ㉡-스포츠로의 사회화 / ㉢-스포츠를 통한 사회화 / ㉣-스포츠 탈사회화"
        },
        {
          "id": 3,
          "content": "㉠-스포츠 탈사회화 / ㉡-스포츠를 통한 사회화 / ㉢-스포츠로의 사회화 / ㉣-스포츠로의 재사회화"
        },
        {
          "id": 4,
          "content": "㉠-스포츠 탈사회화 / ㉡-스포츠로의 사회화 / ㉢-스포츠를 통한 사회화 / ㉣-스포츠로의 재사회화"
        }
      ],
      "answer": [
        3
      ],
      "explanation": {
        "correct": "입문은 **스포츠로의 사회화**(㉢), 참여 중 변화는 **스포츠를 통한 사회화**(㉡), 중단은 **스포츠 탈사회화**(㉠), 복귀는 **스포츠로의 재사회화**(㉣)입니다.",
        "summary": "스포츠 사회화 단계 - Into(로의) → Via(통한) → Out of(탈) → Back into(재)."
      }
    },
    {
      "id": "SSO-2022-5",
      "questionNumber": 5,
      "question": "학원엘리트스포츠를 지지하는 입장이 아닌 것은?",
      "options": [
        {
          "id": 1,
          "content": "애교심을 강화시킬 수 있다."
        },
        {
          "id": 2,
          "content": "학교의 자원 및 교육시설을 독점할 수 있다."
        },
        {
          "id": 3,
          "content": "지위 창출의 수단, 사회이동의 기제로 작용할 수 있다."
        },
        {
          "id": 4,
          "content": "사회에서 요구되는 책임감, 성취감, 적응력 등을 배양시킬 수 있다."
        }
      ],
      "answer": [
        2
      ],
      "explanation": {
        "correct": "**학교 자원 및 시설의 독점**은 일반 학생의 권익을 해치는 학원 스포츠의 대표적 역기능입니다.",
        "distractors": [
          {
            "term": "순기능",
            "reason": "애교심 고취, 사회적 지위 상승 기회, 인성 함양 등이 있습니다."
          }
        ],
        "summary": "학원스포츠의 기능 - 교육적 순기능 vs 반교육적 역기능."
      }
    },
    {
      "id": "SSO-2022-6",
      "questionNumber": 6,
      "question": "<보기>의 내용과 관련이 깊은 사회학 이론은?",
      "view": {
        "text": [
          {
            "text": "미시적 관점의 이론이다."
          },
          {
            "text": "인간은 사회제도나 규칙에 대해 능동적으로 사고하고 의미를 부여하며 행동한다."
          },
          {
            "text": "스포츠 팀의 주장은 리더십이 필요하기 때문에 점차 그 역할에 맞는 리더십을 발휘한다."
          }
        ]
      },
      "options": [
        {
          "id": 1,
          "content": "갈등이론"
        },
        {
          "id": 2,
          "content": "교환이론"
        },
        {
          "id": 3,
          "content": "상징적 상호작용론"
        },
        {
          "id": 4,
          "content": "기능주의이론"
        }
      ],
      "answer": [
        3
      ],
      "explanation": {
        "correct": "**상징적 상호작용론**은 인간이 타인과의 소통을 통해 의미를 창조하고 자신의 역할을 형성해가는 미시적 관점의 이론입니다.",
        "summary": "주요 이론 관점 - 기능주의(안정), 갈등론(불평등), 상징적 상호작용론(개인적 의미)."
      }
    },
    {
      "id": "SSO-2022-7",
      "questionNumber": 7,
      "question": "정치의 스포츠 이용 방법에 관한 설명 중 옳은 것은?",
      "options": [
        {
          "id": 1,
          "content": "태권도를 보면 대한민국 국기(國技)라는 동일화가 일어난다."
        },
        {
          "id": 2,
          "content": "정부의 3S(sports, screen, sex) 정책은 스포츠를 이용하는 상징의 대표적인 방법이다."
        },
        {
          "id": 3,
          "content": "스포츠 이벤트에서 국가 연주, 선수 복장, 국기에 대한 의례 등은 상징의식에 해당한다."
        },
        {
          "id": 4,
          "content": "올림픽에서 금메달 수상 장면을 보면서 내가 획득한 것처럼 눈물을 흘리는 것은 상징화에 해당한다."
        }
      ],
      "answer": [
        3
      ],
      "explanation": {
        "correct": "**상징**은 국가 연주나 의례처럼 특정 가치를 시각적·청각적 기호로 나타내는 정치적 기제입니다.",
        "distractors": [
          {
            "term": "동일화",
            "reason": "태권도를 국가와 일체화하거나 금메달에 감정 이입하는 것."
          },
          {
            "term": "조작",
            "reason": "3S 정책처럼 인위적 환경 조성."
          }
        ],
        "summary": "정치의 스포츠 활용 - 상징, 동일화, 조작."
      }
    },
    {
      "id": "SSO-2022-8",
      "questionNumber": 8,
      "question": "<보기>에서 설명하는 투민(M. Tumin)의 스포츠계층 형성 과정은?",
      "view": {
        "text": [
          {
            "text": "스포츠 종목에서 요구되는 우수한 운동수행능력을 갖추어야 한다."
          },
          {
            "text": "뛰어난 경기력뿐만 아니라 탁월한 개인적 특성을 갖추어야 한다."
          },
          {
            "text": "스포츠 팀 구성원으로 자신의 능력이 팀 승리에 미치는 영향력이 커야 한다."
          }
        ]
      },
      "options": [
        {
          "id": 1,
          "content": "평가"
        },
        {
          "id": 2,
          "content": "지위의 분화"
        },
        {
          "id": 3,
          "content": "보수부여"
        },
        {
          "id": 4,
          "content": "지위의 서열화"
        }
      ],
      "answer": [
        4
      ],
      "explanation": {
        "correct": "**지위의 서열화**는 나뉜 역할들 사이에 가치를 매기고 순위를 결정하는 과정입니다.",
        "summary": "계층 형성 4단계 - 분화 → 서열화 → 평가 → 보수부여."
      }
    },
    {
      "id": "SSO-2022-9",
      "questionNumber": 9,
      "question": "<보기>의 내용과 관련 있는 용어는?",
      "view": {
        "text": [
          {
            "text": "로버트슨(R. Roberston)이 제시한 용어이다."
          },
          {
            "text": "LA 다저스팀이 박찬호 선수를 영입하여 좋은 경기력을 펼치면서 메이저리그 경기가 한국에서 인기가 높아졌다."
          },
          {
            "text": "맨체스터 유나이티드팀이 박지성 선수를 영입하면서 프리미어리그 경기가 한국에서 인기가 높아졌다."
          }
        ]
      },
      "options": [
        {
          "id": 1,
          "content": "세방화(Glocalization)"
        },
        {
          "id": 2,
          "content": "스포츠화(Sportization)"
        },
        {
          "id": 3,
          "content": "미국화(Americanization)"
        },
        {
          "id": 4,
          "content": "세계표준화(Global Standardization)"
        }
      ],
      "answer": [
        1
      ],
      "explanation": {
        "correct": "**세방화(Glocalization)**는 세계화가 현지 문화와 결합하여 독특하게 수용되는 현상입니다.",
        "summary": "글로컬라이제이션 - 글로벌 표준의 현지 최적화."
      }
    },
    {
      "id": "SSO-2022-10",
      "questionNumber": 10,
      "question": "국제사회에서 발생한 스포츠 사건에 관한 설명으로 옳은 것은?",
      "options": [
        {
          "id": 1,
          "content": "남아프리카 공화국은 아파르트헤이트(apartheid)로 인해 국제대회 참여가 거부되었다."
        },
        {
          "id": 2,
          "content": "구소련의 아프가니스탄 침공을 이유로 1984년 LA올림픽경기대회에 많은 자유 진영 국가가 불참하였다."
        },
        {
          "id": 3,
          "content": "2018년 평창동계올림픽경기대회에서 메달 획득을 위해 여자 아이스하키 남북 단일팀이 결성되었다."
        },
        {
          "id": 4,
          "content": "1936년 베를린올림픽경기대회에서 검은구월단 무장단체가 선수촌에 침입하여 이스라엘 선수를 살해하였다."
        }
      ],
      "answer": [
        1
      ],
      "explanation": {
        "correct": "**아파르트헤이트** 정책으로 인해 남아공은 수십 년간 국제 스포츠계에서 퇴출당했습니다.",
        "distractors": [
          {
            "term": "선지 2: 1984년 LA올림픽 보이콧",
            "reason": "구소련의 아프가니스탄 침공(1979)에 항의하여 서방 국가들이 보이콧한 것은 **1980년 모스크바 올림픽**입니다. 1984년 LA올림픽에는 소련·동유럽 진영이 보복 보이콧을 단행했습니다."
          },
          {
            "term": "선지 3: 2018년 평창 남북 단일팀 메달 획득 목적",
            "reason": "2018년 평창동계올림픽 남북 여자 아이스하키 단일팀은 메달 획득이 목적이 아니라 **남북 화합과 평화**를 상징하기 위해 구성된 것입니다."
          },
          {
            "term": "선지 4: 1936년 베를린 올림픽 검은구월단 사건",
            "reason": "검은구월단 사건은 **1936년 베를린 올림픽이 아닌 1972년 뮌헨 올림픽**에서 발생한 팔레스타인 무장조직의 이스라엘 선수단 테러 사건입니다."
          }
        ],
        "summary": "국제 정치적 분쟁 - 보이콧, 테러, 인종차별 정책."
      }
    },
    {
      "id": "SSO-2022-11",
      "questionNumber": 11,
      "question": "<보기>의 설명은 머튼(R. Merton)의 아노미(anomie) 이론에 대한 것이다. ㉠~㉢에 해당하는 적응유형이 바르게 연결된 것은?",
      "view": {
        "list": [
          {
            "label": "ㄱ",
            "content": [
              "도피주의 - 스포츠에 내재된 비인간성, 승리지상주의, 상업주의, 학업 결손 등에 염증을 느껴 스포츠 참가 포기"
            ]
          },
          {
            "label": "㉠",
            "content": [
              "승패에 집착하지 않고 참가에 의의를 두는 것, 결과보다는 경기 내용 중시"
            ]
          },
          {
            "label": "㉡",
            "content": [
              "불법 스카우트, 금지 약물 복용, 경기장 폭력, 승부조작 등"
            ]
          },
          {
            "label": "㉢",
            "content": [
              "전략적 시간 끌기 작전, 경기규칙이 허용하는 범위 내에서의 파울 행위 등"
            ]
          }
        ]
      },
      "options": [
        {
          "id": 1,
          "content": "㉠-혁신주의 / ㉡-동조주의 / ㉢-의례주의"
        },
        {
          "id": 2,
          "content": "㉠-의례주의 / ㉡-혁신주의 / ㉢-동조주의"
        },
        {
          "id": 3,
          "content": "㉠-의례주의 / ㉡-동조주의 / ㉢-혁신주의"
        },
        {
          "id": 4,
          "content": "㉠-혁신주의 / ㉡-의례주의 / ㉢-동조주의"
        }
      ],
      "answer": [
        2
      ],
      "explanation": {
        "correct": "수단에만 매달리는 **의례주의**(㉠), 부정한 수단을 쓰는 **혁신주의**(㉡), 규칙 내에서 경쟁하는 **동조주의**(㉢)입니다.",
        "summary": "머튼의 아노미 적응 유형 5가지."
      }
    },
    {
      "id": "SSO-2022-12",
      "questionNumber": 12,
      "question": "<보기>의 내용을 기든스(A. Giddens)의 사회계층 이동 준거와 유형으로 바르게 묶은 것은?",
      "view": {
        "text": [
          {
            "text": "K는 가난한 가정에서 태어나 끊임없는 훈련을 통해 축구 월드스타가 되었다."
          },
          {
            "text": "월드스타가 되고 난 후, 축구장학재단을 만들어 개발도상국에 축구학교를 설립하여 후진양성에 큰 역할을 하고 있다."
          }
        ]
      },
      "options": [
        {
          "id": 1,
          "content": "이동 주체-개인 / 이동 방향-수직이동 / 시간적거리-세대내이동"
        },
        {
          "id": 2,
          "content": "이동 주체-개인 / 이동 방향-수평이동 / 시간적거리-세대간이동"
        },
        {
          "id": 3,
          "content": "이동 주체-집단 / 이동 방향-수직이동 / 시간적거리-세대간이동"
        },
        {
          "id": 4,
          "content": "이동 주체-집단 / 이동 방향-수평이동 / 시간적거리-세대내이동"
        }
      ],
      "answer": [
        1
      ],
      "explanation": {
        "correct": "K 개인의 지위가 생애 동안 수직으로 상승했으므로 **개인-수직-세대 내 이동**입니다.",
        "summary": "사회 이동의 종류와 준거."
      }
    },
    {
      "id": "SSO-2022-13",
      "questionNumber": 13,
      "question": "<보기>에서 설명하는 스포츠 미디어 이론은?",
      "view": {
        "text": [
          {
            "text": "대중들은 능동적 수용자로서 특수한 심리적 욕구를 만족시키기 위해 매스미디어를 적극 이용한다."
          },
          {
            "text": "이에 미디어 수용자는 인지적, 정의적, 도피적, 통합적 욕구를 충족시키기 위해 스포츠를 주제로 다루는 매스미디어를 이용한다."
          }
        ]
      },
      "options": [
        {
          "id": 1,
          "content": "사회범주이론"
        },
        {
          "id": 2,
          "content": "개인차이론"
        },
        {
          "id": 3,
          "content": "사회관계이론"
        },
        {
          "id": 4,
          "content": "문화규범이론"
        }
      ],
      "answer": [
        2
      ],
      "explanation": {
        "correct": "수용자의 능동적 선택과 욕구 충족을 강조하는 **개인차이론(이용과 충족 이론)**입니다.",
        "summary": "미디어의 수용자 유형과 효과."
      }
    },
    {
      "id": "SSO-2022-14",
      "questionNumber": 14,
      "question": "<보기>에서 코클리(J. Coakley)가 제시한 상업주의와 관련된 스포츠 규칙 변화의 충족 조건으로 옳은 것만을 모두 고른 것은?",
      "view": {
        "list": [
          {
            "label": "㉠",
            "content": [
              "경기의 속도감 향상"
            ]
          },
          {
            "label": "㉡",
            "content": [
              "관중의 흥미 극대화"
            ]
          },
          {
            "label": "㉢",
            "content": [
              "득점 방법의 단일화"
            ]
          },
          {
            "label": "㉣",
            "content": [
              "상업적인 광고 시간 할애"
            ]
          }
        ]
      },
      "options": [
        {
          "id": 1,
          "content": "㉠, ㉡"
        },
        {
          "id": 2,
          "content": "㉢, ㉣"
        },
        {
          "id": 3,
          "content": "㉠, ㉡, ㉢"
        },
        {
          "id": 4,
          "content": "㉠, ㉡, ㉣"
        }
      ],
      "answer": [
        4
      ],
      "explanation": {
        "correct": "속도 향상(㉠), 흥미 유발(㉡), 광고 시간(㉣) 확보를 위해 규칙이 바뀝니다.",
        "distractors": [
          {
            "term": "㉢",
            "reason": "득점 방식은 오히려 더 다양해지는 경향이 있습니다."
          }
        ],
        "summary": "스포츠 상업화의 규칙 변용."
      }
    },
    {
      "id": "SSO-2022-15",
      "questionNumber": 15,
      "question": "<보기>에서 설명하는 프로스포츠의 제도는?",
      "view": {
        "text": [
          {
            "text": "프로스포츠리그의 신인선수 선발 방식 중 하나이다."
          },
          {
            "text": "신인선수 쟁탈에 따른 폐단을 막기 위해 도입되었다."
          },
          {
            "text": "계약금 인상 경쟁을 막기 위한 방법으로 고안되었다."
          }
        ]
      },
      "options": [
        {
          "id": 1,
          "content": "FA(free agent)"
        },
        {
          "id": 2,
          "content": "샐러리 캡(salary cap)"
        },
        {
          "id": 3,
          "content": "드래프트(draft)"
        },
        {
          "id": 4,
          "content": "최저연봉(minimum salary)"
        }
      ],
      "answer": [
        3
      ],
      "explanation": {
        "correct": "구단의 독점과 과열 경쟁을 막는 **드래프트** 제도입니다.",
        "summary": "프로스포츠 리그의 전력 평준화 장치."
      }
    },
    {
      "id": "SSO-2022-16",
      "questionNumber": 16,
      "question": "<보기>에서 대중매체가 스포츠에 미치는 영향에 해당되는 것만을 모두 고른 것은?",
      "view": {
        "list": [
          {
            "label": "㉠",
            "content": [
              "대중매체의 기술이 발전한다."
            ]
          },
          {
            "label": "㉡",
            "content": [
              "스포츠 인구가 증가한다."
            ]
          },
          {
            "label": "㉢",
            "content": [
              "새로운 스포츠 종목이 창출된다."
            ]
          },
          {
            "label": "㉣",
            "content": [
              "미디어 콘텐츠를 제공한다."
            ]
          },
          {
            "label": "㉤",
            "content": [
              "경기규칙과 경기일정이 변경된다."
            ]
          },
          {
            "label": "㉥",
            "content": [
              "스포츠 용구가 변화한다."
            ]
          }
        ]
      },
      "options": [
        {
          "id": 1,
          "content": "㉠, ㉡, ㉢"
        },
        {
          "id": 2,
          "content": "㉠, ㉢, ㉣"
        },
        {
          "id": 3,
          "content": "㉡, ㉢, ㉣, ㉤"
        },
        {
          "id": 4,
          "content": "㉡, ㉢, ㉤, ㉥"
        }
      ],
      "answer": [
        4
      ],
      "explanation": {
        "correct": "미디어로 인한 참여 확대(㉡), 신규 종목(㉢), 규칙/일정 변경(㉤), 시각적 용구 변화(㉥)가 해당합니다.",
        "summary": "스포츠와 미디어의 상호 영향 관계."
      }
    },
    {
      "id": "SSO-2022-17",
      "questionNumber": 17,
      "question": "스포츠의 교육적 순기능 중 사회선도 기능이 아닌 것은?",
      "options": [
        {
          "id": 1,
          "content": "여권신장"
        },
        {
          "id": 2,
          "content": "학교 내 통합"
        },
        {
          "id": 3,
          "content": "평생체육과의 연계"
        },
        {
          "id": 4,
          "content": "장애인의 삶의 질 향상"
        }
      ],
      "answer": [
        2
      ],
      "explanation": {
        "correct": "**학교 내 통합**은 사회 전체를 이끄는 '선도'보다는 조직 '내부 결속' 기능입니다.",
        "summary": "스포츠의 사회 선도 역할 - 평등, 보건, 복지 실현."
      }
    },
    {
      "id": "SSO-2022-18",
      "questionNumber": 18,
      "question": "다음 ㉠~㉣에서 코클리(J. Coakley)가 제시한 일탈적 과잉동조를 유발하는 스포츠 윤리규범의 유형과 특징으로 옳은 것만을 모두 고른 것은?",
      "view": {
        "list": [
          {
            "label": "㉠",
            "content": [
              "구분짓기규범 - 다른 선수와 구별되기 위해 탁월성을 추구해야 한다."
            ]
          },
          {
            "label": "㉡",
            "content": [
              "인내규범 - 위험을 받아들이고 고통 속에서도 경기에 참여해야 한다."
            ]
          },
          {
            "label": "㉢",
            "content": [
              "몰입규범 - 경기에 헌신해야 하며 이를 그들의 삶에서 우선순위에 두어야 한다."
            ]
          },
          {
            "label": "㉣",
            "content": [
              "도전규범 - 스포츠에서 성공을 위해 장애를 극복하고 역경을 헤쳐 나가야 한다."
            ]
          }
        ]
      },
      "options": [
        {
          "id": 1,
          "content": "㉠, ㉡"
        },
        {
          "id": 2,
          "content": "㉡, ㉢"
        },
        {
          "id": 3,
          "content": "㉠, ㉢, ㉣"
        },
        {
          "id": 4,
          "content": "㉠, ㉡, ㉢, ㉣"
        }
      ],
      "answer": [
        4
      ],
      "explanation": {
        "correct": "코클리의 4대 윤리규범이 모두 정확히 설명되어 있습니다.",
        "summary": "긍정적 일탈의 원인인 스포츠 에토스 수용."
      }
    },
    {
      "id": "SSO-2022-19",
      "questionNumber": 19,
      "question": "맥루한(M. McLuhan)의 매체이론에 관한 설명으로 옳지 않은 것은?",
      "options": [
        {
          "id": 1,
          "content": "핫(hot) 미디어 스포츠는 관람자의 감각 참여성이 낮다."
        },
        {
          "id": 2,
          "content": "쿨(cool) 미디어 스포츠는 관람자의 감각 몰입성이 높다."
        },
        {
          "id": 3,
          "content": "핫(hot) 미디어 스포츠는 경기 진행 속도가 빠르다."
        },
        {
          "id": 4,
          "content": "쿨(cool) 미디어 스포츠는 메시지의 정의성이 낮다."
        }
      ],
      "answer": [
        3
      ],
      "explanation": {
        "correct": "**핫 미디어**는 정적인 종목에 가깝고, 진행이 빠른 종목은 **쿨 미디어** 특성을 띱니다.",
        "summary": "맥루한의 미디어 분류 체계."
      }
    },
    {
      "id": "SSO-2022-20",
      "questionNumber": 20,
      "question": "스포츠 세계화의 특징으로 옳지 않은 것은?",
      "options": [
        {
          "id": 1,
          "content": "스포츠 시장의 경계가 국경을 초월해 전 세계로 확대되었다."
        },
        {
          "id": 2,
          "content": "모든 나라의 전통스포츠(folk sports)가 세계적으로 확대되었다."
        },
        {
          "id": 3,
          "content": "세계인이 표준화된 스포츠 상품과 스포츠 문화를 소비하게 되었다."
        },
        {
          "id": 4,
          "content": "프로스포츠 시장의 이윤 극대화로 빈익빈 부익부 현상이 심화되었다."
        }
      ],
      "answer": [
        2
      ],
      "explanation": {
        "correct": "세계화는 **전통 스포츠의 소외**와 문화적 획일화를 초래하기도 합니다.",
        "summary": "스포츠 세계화의 순기능과 역기능."
      }
    }
  ]
}